Metadata-Version: 2.1
Name: simple_multicall_2
Version: 0.1.1
Summary: Simple Web3 multicall 2
Author: 
Author-email: 
License: MIT
Keywords: multicall,web3,multicall2
Classifier: Development Status :: 3 - Alpha
Classifier: Intended Audience :: Developers
Classifier: License :: OSI Approved :: MIT License
Classifier: Natural Language :: English
Classifier: Programming Language :: Python :: 3
Requires: Web3
License-File: LICENSE
